clonenotebooks/utils.py
clonenotebooks/cloners/__init__.py
clonenotebooks/cloners/cloners.py
clonenotebooks/cloners/jupyter-config/jupyter_notebook_config.d/cloners.json
clonenotebooks/renderers/__init__.py
clonenotebooks/renderers/renderers.py
clonenotebooks-1.0.3.data/data/etc/jupyter/jupyter_notebook_config.d/cloners.json
clonenotebooks-1.0.3.dist-info/LICENSE
clonenotebooks-1.0.3.dist-info/METADATA
clonenotebooks-1.0.3.dist-info/WHEEL
clonenotebooks-1.0.3.dist-info/top_level.txt
clonenotebooks-1.0.3.dist-info/RECORD
