Metadata-Version: 2.1
Name: clonenotebooks
Version: 1.0.3
Summary: NBViewer extension and Jupyter notebook extension for cloning notebooks viewed in NBViewer to user's home directory.
Home-page: https://github.com/krinsman/clonenotebooks
Author: William Krinsman
Author-email: krinsman@berkeley.edu
License: BSD
Platform: UNKNOWN
Classifier: Programming Language :: Python :: 3
Classifier: Programming Language :: Python :: 3.7
Classifier: Programming Language :: Python :: 3.8
Classifier: License :: OSI Approved :: BSD License
Requires-Dist: nbviewer
Requires-Dist: notebook
Requires-Dist: jupyterhub
Requires-Dist: nbformat
Requires-Dist: tornado
Requires-Dist: jupyter-client
